type_extension_package/__init__.py
type_extension_package/typing_extensions.py
typing_extensions_plus-3.1.3.dist-info/LICENSE
typing_extensions_plus-3.1.3.dist-info/METADATA
typing_extensions_plus-3.1.3.dist-info/WHEEL
typing_extensions_plus-3.1.3.dist-info/top_level.txt
typing_extensions_plus-3.1.3.dist-info/RECORD
