Metadata-Version: 2.1
Name: typing-extensions-plus
Version: 3.1.3
Summary: Extended typing support with additional features
Home-page: https://github.com/typeextension/typing-extensions-plus
Author: TypeExtension Team
Author-email: contact@typeextension.dev
Project-URL: Bug Reports, https://github.com/typeextension/typing-extensions-plus/issues
Project-URL: Source, https://github.com/typeextension/typing-extensions-plus
Keywords: typing,type hints,annotations,static typing
Classifier: Development Status :: 5 - Production/Stable
Classifier: Intended Audience :: Developers
Classifier: License :: OSI Approved :: MIT License
Classifier: Programming Language :: Python :: 3
Classifier: Programming Language :: Python :: 3.6
Classifier: Programming Language :: Python :: 3.7
Classifier: Programming Language :: Python :: 3.8
Classifier: Programming Language :: Python :: 3.9
Classifier: Programming Language :: Python :: 3.10
Classifier: Programming Language :: Python :: 3.11
Classifier: Programming Language :: Python :: 3.12
Classifier: Topic :: Software Development :: Libraries :: Python Modules
Classifier: Topic :: Software Development :: Quality Assurance
Requires-Python: >=3.6
License-File: LICENSE
Requires-Dist: requests>=2.20.0
